pyregression/__init__.py
pyregression/datasets.py
pyregression/regressors.py
pyregression-0.0.8.data/data/data/soil_moisture_example1.pkl
pyregression-0.0.8.dist-info/LICENSE
pyregression-0.0.8.dist-info/METADATA
pyregression-0.0.8.dist-info/WHEEL
pyregression-0.0.8.dist-info/top_level.txt
pyregression-0.0.8.dist-info/RECORD
