Metadata-Version: 2.1
Name: pyregression
Version: 0.0.8
Summary: Machine learning regressions methods
Home-page: https://gitlab.com/pyregression/pyregression
Author: Emiliano Lopez
Author-email: emiliano.lopez@gmail.com
License: UNKNOWN
Platform: UNKNOWN
Classifier: Programming Language :: Python :: 3
Classifier: License :: OSI Approved :: GNU General Public License v3 (GPLv3)
Classifier: Operating System :: OS Independent
Requires-Python: >=3.6
